sweepystats/__init__.py
sweepystats/anova.py
sweepystats/gaussian.py
sweepystats/linreg.py
sweepystats/sweep_matrix.py
sweepystats/util.py
sweepystats-0.0.10.dist-info/LICENSE
sweepystats-0.0.10.dist-info/METADATA
sweepystats-0.0.10.dist-info/WHEEL
sweepystats-0.0.10.dist-info/top_level.txt
sweepystats-0.0.10.dist-info/RECORD
