Metadata-Version: 2.1
Name: sweepystats
Version: 0.0.10
Summary: Python package to perform the statistical sweep operation on symmetric numpy matrices
Author-email: Benjamin Chu <benchu99@hotmail.com>
License: MIT License
Project-URL: Homepage, https://github.com/biona001/sweepystats
Project-URL: Documentation, https://biona001.github.io/sweepystats
Project-URL: Issues, https://github.com/biona001/sweepystats/issues
Keywords: sweep,matrix inverse,determinant,regression,ANOVA
Classifier: Programming Language :: Python :: 3
Classifier: License :: OSI Approved :: MIT License
Classifier: Operating System :: OS Independent
Requires-Python: >=3.8
License-File: LICENSE
Requires-Dist: numpy>=1.20
Requires-Dist: scipy>=1.10.1
Requires-Dist: tqdm>=4.0
Requires-Dist: pandas>=1.0
Requires-Dist: patsy>=0.5
